CHANGELOG.md
LICENSE
MANIFEST.in
README.md
setup.cfg
setup.py
osmosis_driver_interface/__init__.py
osmosis_driver_interface/computing_plugin.py
osmosis_driver_interface/constants.py
osmosis_driver_interface/data_plugin.py
osmosis_driver_interface/exceptions.py
osmosis_driver_interface/log.py
osmosis_driver_interface/osmosis.py
osmosis_driver_interface/utils.py
osmosis_driver_interface_plus.egg-info/PKG-INFO
osmosis_driver_interface_plus.egg-info/SOURCES.txt
osmosis_driver_interface_plus.egg-info/dependency_links.txt
osmosis_driver_interface_plus.egg-info/not-zip-safe
osmosis_driver_interface_plus.egg-info/requires.txt
osmosis_driver_interface_plus.egg-info/top_level.txt
tests/__init__.py
tests/osmosis.ini
tests/test_osmosis_driver.py
tests/test_url_parser.py
tests/test_utils.py