Metadata-Version: 2.1
Name: osmosis-driver-interface-plus
Version: 0.0.9
Summary: 💧 Osmosis driver interface. A membrane between the decentralized world and centralized world. Extended with support for custom drivers.
Home-page: https://github.com/marcojrfurtado/osmosis-driver-interface-plus
Author: marcojrfurtado
Author-email: devops@oceanprotocol.com
License: Apache Software License 2.0
Keywords: osmosis-driver-interface-plus
Platform: UNKNOWN
Classifier: Development Status :: 2 - Pre-Alpha
Classifier: Intended Audience :: Developers
Classifier: License :: OSI Approved :: Apache Software License
Classifier: Natural Language :: English
Classifier: Programming Language :: Python :: 3.5
Classifier: Programming Language :: Python :: 3.6
Provides-Extra: dev
Provides-Extra: test
